Testchatpkg/__init__.py
Win_Chat_Package-1.0.dist-info/LICENSE
Win_Chat_Package-1.0.dist-info/METADATA
Win_Chat_Package-1.0.dist-info/WHEEL
Win_Chat_Package-1.0.dist-info/top_level.txt
Win_Chat_Package-1.0.dist-info/RECORD
